fdc_unit_converter/__init__.py
fdc_unit_converter/magnitudes.py
fdc_unit_converter/unit_converter.py
fdc_unit_converter/units.py
fdc_unit_converter-1.0.0.dist-info/LICENSE
fdc_unit_converter-1.0.0.dist-info/METADATA
fdc_unit_converter-1.0.0.dist-info/WHEEL
fdc_unit_converter-1.0.0.dist-info/RECORD
