Metadata-Version: 2.3
Name: fdc-unit-converter
Version: 1.0.0
Summary: A flexible unit conversion library for scientific and engineering use
License: MIT
Author: Ariel Cabello
Author-email: acabello@fdc-group.com
Requires-Python: >=3.9
Classifier: License :: OSI Approved :: MIT License
Classifier: Programming Language :: Python :: 3
Classifier: Programming Language :: Python :: 3.9
Classifier: Programming Language :: Python :: 3.10
Classifier: Programming Language :: Python :: 3.11
Classifier: Programming Language :: Python :: 3.12
Classifier: Programming Language :: Python :: 3.13
Requires-Dist: numpy
Requires-Dist: pandas
Project-URL: Homepage, https://github.com/fdc-dash/fdc-unit-converter
Project-URL: Issues, https://github.com/fdc-dash/fdc-unit-converter/issues
